run.py
run_experiments-1.0.8.dist-info/licenses/LICENSE
run_experiments-1.0.8.dist-info/METADATA
run_experiments-1.0.8.dist-info/WHEEL
run_experiments-1.0.8.dist-info/top_level.txt
run_experiments-1.0.8.dist-info/RECORD
