Metadata-Version: 2.4
Name: run-experiments
Version: 1.0.8
Summary: python module for running experiments
Author-email: Thomas Bläsius <thomas.blaesius@kit.edu>
License-Expression: ISC
Project-URL: Homepage, https://github.com/thobl/run
Project-URL: Documentation, https://thobl.github.io/run/
License-File: LICENSE
Requires-Dist: filelock
Requires-Dist: tqdm
Requires-Dist: pathos
Dynamic: license-file
